crud/__init__.py
crud/admin.py
crud/apps.py
crud/managers.py
crud/models.py
crud/tests.py
crud/utils.py
crud/views.py
crud/migrations/__init__.py
scrud/__init__.py
scrud/admin.py
scrud/apps.py
scrud/managers.py
scrud/models.py
scrud/tests.py
scrud/utils.py
scrud/views.py
scrud/migrations/__init__.py
drf_scrud-1.0.dist-info/LICENSE
drf_scrud-1.0.dist-info/METADATA
drf_scrud-1.0.dist-info/WHEEL
drf_scrud-1.0.dist-info/top_level.txt
drf_scrud-1.0.dist-info/RECORD
