Metadata-Version: 2.1
Name: drf-scrud
Version: 1.0
Summary: Django Rest Framework SCRUD viewset.
Home-page: https://github.com/shadow3312/drf-scrud
Author: Shuruzer
Author-email: eludeceti@gmail.com
Maintainer: Shuruzer
Maintainer-email: eludeceti@gmail.com
License: MIT
Keywords: django drf crud drf-crud custom viewset
Classifier: Environment :: Web Environment
Classifier: Framework :: Django
Classifier: Intended Audience :: Developers
Classifier: License :: OSI Approved :: MIT License
Classifier: Operating System :: OS Independent
Classifier: Programming Language :: Python :: 3
Classifier: Programming Language :: Python :: 3 :: Only
Classifier: Programming Language :: Python :: 3.5
Classifier: Programming Language :: Python :: 3.6
Classifier: Programming Language :: Python :: 3.7
Classifier: Programming Language :: Python :: 3.8
Classifier: Programming Language :: Python :: 3.9
Classifier: Programming Language :: Python :: 3.10
Classifier: Topic :: Software Development :: Libraries :: Python Modules
License-File: LICENSE
